jdu/__init__.py
jdu/api/__init__.py
jdu/api/base.py
jdu/api/open/__init__.py
jdu/api/open/category.py
jdu/api/open/goods.py
jdu/api/open/order.py
jdu/api/open/promotion.py
jdu/api/web/__init__.py
jdu/api/web/goods.py
jdu/api/web/m.py
jdu/api/web/receive_code.py
jdu/client/__init__.py
jdu/client/base.py
jdu/client/open.py
jdu/client/web.py
jdu/core/__init__.py
jdu/core/exceptions.py
jdu/core/utils.py
jdu-0.0.1b2.dist-info/METADATA
jdu-0.0.1b2.dist-info/WHEEL
jdu-0.0.1b2.dist-info/top_level.txt
jdu-0.0.1b2.dist-info/RECORD
